odoo9_addon_website_field_autocomplete-9.0.1.0.1.99.dev18-py2.7-nspkg.pth
odoo9_addon_website_field_autocomplete-9.0.1.0.1.99.dev18.dist-info/METADATA
odoo9_addon_website_field_autocomplete-9.0.1.0.1.99.dev18.dist-info/RECORD
odoo9_addon_website_field_autocomplete-9.0.1.0.1.99.dev18.dist-info/WHEEL
odoo9_addon_website_field_autocomplete-9.0.1.0.1.99.dev18.dist-info/namespace_packages.txt
odoo9_addon_website_field_autocomplete-9.0.1.0.1.99.dev18.dist-info/top_level.txt
odoo_addons/website_field_autocomplete/README.rst
odoo_addons/website_field_autocomplete/__init__.py
odoo_addons/website_field_autocomplete/__openerp__.py
odoo_addons/website_field_autocomplete/controllers/__init__.py
odoo_addons/website_field_autocomplete/controllers/main.py
odoo_addons/website_field_autocomplete/demo/field_autocomplete_demo.xml
odoo_addons/website_field_autocomplete/i18n/ca.po
odoo_addons/website_field_autocomplete/i18n/de.po
odoo_addons/website_field_autocomplete/i18n/es.po
odoo_addons/website_field_autocomplete/i18n/fi.po
odoo_addons/website_field_autocomplete/i18n/fr.po
odoo_addons/website_field_autocomplete/i18n/it.po
odoo_addons/website_field_autocomplete/i18n/nb_NO.po
odoo_addons/website_field_autocomplete/i18n/pt_BR.po
odoo_addons/website_field_autocomplete/i18n/sl.po
odoo_addons/website_field_autocomplete/i18n/tr.po
odoo_addons/website_field_autocomplete/i18n/website_field_autocomplete.pot
odoo_addons/website_field_autocomplete/i18n/zh_CN.po
odoo_addons/website_field_autocomplete/static/description/icon.png
odoo_addons/website_field_autocomplete/static/src/js/field_autocomplete.js
odoo_addons/website_field_autocomplete/views/assets.xml
