Metadata-Version: 2.1
Name: odoo9-addon-website-field-autocomplete
Version: 9.0.1.0.1.99.dev18
Summary: Provides an autocomplete field for Website on any model
Home-page: https://laslabs.com/
Author: LasLabs, Odoo Community Association (OCA)
Author-email: support@odoo-community.org
License: AGPL-3
Platform: UNKNOWN
Classifier: Programming Language :: Python
Classifier: Framework :: Odoo
Classifier: License :: OSI Approved :: GNU Affero General Public License v3
Requires-Python: ~=2.7
Requires-Dist: odoo (<9.1a,>=9.0a)
